opaw/__init__.py
opaw/main.py
opaw/examples/__init__.py
opaw/examples/audio.py
opaw/examples/basic.py
opaw/examples/chat.py
opaw/examples/completion.py
opaw/examples/edit.py
opaw/examples/embedding.py
opaw/examples/file.py
opaw/examples/finetune.py
opaw/examples/funcs.py
opaw/examples/function_call.py
opaw/examples/image.py
opaw/examples/load-chat.py
opaw/examples/moderation.py
opaw/model/__init__.py
opaw/model/audio.py
opaw/model/bot.py
opaw/model/chat.py
opaw/model/completion.py
opaw/model/edit.py
opaw/model/embedding.py
opaw/model/file.py
opaw/model/finetune.py
opaw/model/image.py
opaw/model/moderation.py
opaw/test/__init__.py
opaw/test/audio-hist.py
opaw/test/test.py
opaw/test/test2.py
opaw/tool/__init__.py
opaw/tool/stock.py
opaw/util/__init__.py
opaw/util/log.py
opaw-0.4.5.dist-info/LICENSE
opaw-0.4.5.dist-info/METADATA
opaw-0.4.5.dist-info/WHEEL
opaw-0.4.5.dist-info/top_level.txt
opaw-0.4.5.dist-info/RECORD
